LICENSE.txt
MANIFEST.in
kicadsearchrc.sample
setup.py
bin/kicadsearch
bin/kicadsearch-index
kicadsearch/__init__.py
kicadsearch/kicadsearch_config.py
kicadsearch/kicadsearch_index.py
kicadsearch/kicadsearch_parser.py
kicadsearch/kicadsearch_search.py
kicadsearch.egg-info/PKG-INFO
kicadsearch.egg-info/SOURCES.txt
kicadsearch.egg-info/dependency_links.txt
kicadsearch.egg-info/requires.txt
kicadsearch.egg-info/top_level.txt
test/test_kicadsearch_config.py
test/test_kicadsearch_index.py
test/test_kicadsearch_parser.py
test/test_kicadsearch_search.py