Metadata-Version: 1.0
Name: kicadsearch
Version: 0.3.1
Summary: Freetext searching in KiCad EDA component libraries
Home-page: https://github.com/arvjus/kicad-search
Author: Arvid Juskaitis
Author-email: arvydas.juskaitis@gmail.com
License: LICENSE.txt
Keywords: kicad,search
Platform: UNKNOWN
